nts/logging/__init__.py
nts/logging/basic_handler.py
nts/logging/formatter.py
nts/logging/redis_handler.py
nts.logging-0.0.1.dist-info/LICENSE
nts.logging-0.0.1.dist-info/METADATA
nts.logging-0.0.1.dist-info/WHEEL
nts.logging-0.0.1.dist-info/top_level.txt
nts.logging-0.0.1.dist-info/RECORD
