Metadata-Version: 2.1
Name: nts.logging
Version: 0.0.1
Summary: Asyncio logging handlers
Author-email: Anton Bondarenko <bond.anton@gmail.com>
License: MIT License
Project-URL: Homepage, https://github.com/bond-anton/nts.logging
Project-URL: Bug Tracker, https://github.com/bond-anton/nts.logging/issues
Classifier: Programming Language :: Python :: 3
Classifier: License :: OSI Approved :: MIT License
Classifier: Operating System :: OS Independent
Requires-Python: >=3.9
License-File: LICENSE
Provides-Extra: all
Requires-Dist: redis >=4.2.0 ; extra == 'all'
Provides-Extra: lint
Requires-Dist: pylint ; extra == 'lint'
Provides-Extra: redis
Requires-Dist: redis >=4.2.0 ; extra == 'redis'
Provides-Extra: test
Requires-Dist: flake8 ; extra == 'test'
Requires-Dist: pytest ; extra == 'test'
Requires-Dist: pytest-asyncio ; extra == 'test'
